<?xml version="1.0" encoding="utf-8" ?><dwsync><file name="index.html" server="ergob.tilaa.cloud:22022//demo10.ergo-sum.tv/html/ajaxJquery/" local="3661435683" remote="3661435686" Dst="-1" /><file name=".DS_Store" server="ergob.tilaa.cloud:22022//demo10.ergo-sum.tv/html/ajaxJquery/" local="3620110172" remote="3661434003" Dst="-1" /><file name="random_portfolio.php" server="ergob.tilaa.cloud:22022//demo10.ergo-sum.tv/html/ajaxJquery/" local="3614434784" remote="3661434003" Dst="-1" /><file name="LICENSE" server="ergob.tilaa.cloud:22022//demo10.ergo-sum.tv/html/ajaxJquery/" local="3618889002" remote="3661434003" Dst="-1" /><file name="README.md" server="ergob.tilaa.cloud:22022//demo10.ergo-sum.tv/html/ajaxJquery/" local="3618889002" remote="3661434007" Dst="-1" /><file name=".gitignore" server="ergob.tilaa.cloud:22022//demo10.ergo-sum.tv/html/ajaxJquery/" local="3618889002" remote="3661434010" Dst="-1" /><file name="package-lock.json" server="ergob.tilaa.cloud:22022//demo10.ergo-sum.tv/html/ajaxJquery/" local="3618889002" remote="3661434010" Dst="-1" /><file name="package.json" server="ergob.tilaa.cloud:22022//demo10.ergo-sum.tv/html/ajaxJquery/" local="3618889002" remote="3661434010" Dst="-1" /><file name="titles.php" server="ergob.tilaa.cloud:22022//demo10.ergo-sum.tv/html/ajaxJquery/" local="3614443766" remote="3661434010" Dst="-1" /><file name="gulpfile.js" server="ergob.tilaa.cloud:22022//demo10.ergo-sum.tv/html/ajaxJquery/" local="3618889002" remote="3661434010" Dst="-1" /><file name=".travis.yml" server="ergob.tilaa.cloud:22022//demo10.ergo-sum.tv/html/ajaxJquery/" local="3618889002" remote="3661434010" Dst="-1" /></dwsync>